lucupy/__init__.py
lucupy/decorators/__init__.py
lucupy/helpers/__init__.py
lucupy/meta/__init__.py
lucupy/minimodel/__init__.py
lucupy/minimodel/atom.py
lucupy/minimodel/constraints.py
lucupy/minimodel/group.py
lucupy/minimodel/ids.py
lucupy/minimodel/magnitude.py
lucupy/minimodel/obs_filter.py
lucupy/minimodel/observation.py
lucupy/minimodel/observationmode.py
lucupy/minimodel/program.py
lucupy/minimodel/qastate.py
lucupy/minimodel/resource.py
lucupy/minimodel/resource_type.py
lucupy/minimodel/semester.py
lucupy/minimodel/site.py
lucupy/minimodel/target.py
lucupy/minimodel/timeallocation.py
lucupy/minimodel/timingwindow.py
lucupy/minimodel/too.py
lucupy/minimodel/wavelength.py
lucupy/observatory/__init__.py
lucupy/observatory/abstract/__init__.py
lucupy/observatory/gemini/__init__.py
lucupy/observatory/gemini/geminiobservation.py
lucupy/observatory/gemini/geminiproperties.py
lucupy/resource_manager/__init__.py
lucupy/resource_manager/resource_manager.py
lucupy/sky/__init__.py
lucupy/sky/altitude.py
lucupy/sky/brightness.py
lucupy/sky/constants.py
lucupy/sky/events.py
lucupy/sky/moon.py
lucupy/sky/sun.py
lucupy/sky/utils.py
lucupy/timeutils/__init__.py
lucupy/types/__init__.py
lucupy-0.2.8.dist-info/METADATA
lucupy-0.2.8.dist-info/WHEEL
lucupy-0.2.8.dist-info/licenses/LICENSE
lucupy-0.2.8.dist-info/RECORD
