Metadata-Version: 2.4
Name: lucupy
Version: 0.2.8
Summary: Lucuma core package for the Gemini Automated Scheduler at: https://github.com/gemini-hlsw/scheduler
License-File: LICENSE
Keywords: lucuma,scheudule,gpp
Author: Sergio Troncoso
Author-email: sergio.troncoso@noirlab.edu
Requires-Python: >=3.11,<4.0
Classifier: Environment :: Web Environment
Classifier: Framework :: Hypothesis
Classifier: Framework :: Pytest
Classifier: Intended Audience :: Science/Research
Classifier: Programming Language :: Python :: 3
Classifier: Programming Language :: Python :: 3.11
Classifier: Programming Language :: Python :: 3.12
Classifier: Programming Language :: Python :: 3.13
Classifier: Programming Language :: Python :: 3.14
Classifier: Programming Language :: Python :: 3.10
Classifier: Topic :: Scientific/Engineering :: Astronomy
Classifier: Topic :: Utilities
Requires-Dist: astropy (>=7.1,<8.0)
Requires-Dist: gelidum (>=0.5.8,<0.6.0)
Project-URL: Homepage, https://github.com/gemini-hlsw/lucupy
Project-URL: Repository, https://github.com/gemini-hlsw/lucupy
